examples/bouncing_ball.py
examples/jay1993.py
examples/jay1995.py
examples/pendulum.py
examples/robertson.py
examples/van_der_pol.py
pydaes/__init__.py
pydaes/integrate/__init__.py
pydaes/integrate/_dae/__init__.py
pydaes/integrate/_dae/base.py
pydaes/integrate/_dae/bdf.py
pydaes/integrate/_dae/common.py
pydaes/integrate/_dae/dae.py
pydaes/integrate/_dae/radau.py
test/test_.py
test/test_dae.py
pydaes-0.0.4.dist-info/LICENSE.txt
pydaes-0.0.4.dist-info/METADATA
pydaes-0.0.4.dist-info/WHEEL
pydaes-0.0.4.dist-info/top_level.txt
pydaes-0.0.4.dist-info/RECORD
