Metadata-Version: 2.1
Name: pydaes
Version: 0.0.4
Summary: Python implementation of solvers for differential algebraic equation's (DAEs) that should be added to scipy one day.
Author-email: Jonas Breuling <jonas.breuling@inm.uni-stuttgart.de>
Project-URL: Homepage, https://github.com/JonasBreuling/pydaes
Project-URL: Issues, https://github.com/JonasBreuling/pydaes/issues
Classifier: Programming Language :: Python :: 3
Classifier: License :: OSI Approved :: BSD License
Classifier: Operating System :: OS Independent
Requires-Python: >=3.8
License-File: LICENSE.txt
Requires-Dist: numpy >=1.24.4
Requires-Dist: scipy >=1.10.1
Requires-Dist: matplotlib >=3.4.3
Provides-Extra: dev
Requires-Dist: pytest ; extra == 'dev'
Requires-Dist: pytest-cov ; extra == 'dev'
